pdfparser/__init__.py
pdfparser/__main__.py
pdfparser/custom_error.py
pdfparser/main_operations.py
pdfparser/user_choice.py
pdfparser/user_inputs.py
pdfparser/utilities.py
sg_pdfparser-1.0.2.dist-info/LICENSE
sg_pdfparser-1.0.2.dist-info/METADATA
sg_pdfparser-1.0.2.dist-info/WHEEL
sg_pdfparser-1.0.2.dist-info/entry_points.txt
sg_pdfparser-1.0.2.dist-info/top_level.txt
sg_pdfparser-1.0.2.dist-info/RECORD
