Metadata-Version: 2.1
Name: sg-pdfparser
Version: 1.0.2
Summary: A Command Line tool for parsing PDFs.
Home-page: https://github.com/uditvashisht/sg-pdfparser
Author: Udit Vashisht
Author-email: admin@saralgyaan.com
License: MIT
Platform: UNKNOWN
Classifier: License :: OSI Approved :: MIT License
Classifier: Programming Language :: Python :: 3.6
Classifier: Programming Language :: Python :: 3.7
Classifier: Programming Language :: Python :: 3.8
Requires-Dist: pypdf2
Requires-Dist: colorama
